core/__init__.py
core/styles.py
core/widgets.py
core/window.py
themes/__init__.py
themes/blue_theme.py
themes/dark_theme.py
themes/light_theme.py
utils/__init__.py
utils/utils.py
custompyqt6-0.1.0.dist-info/METADATA
custompyqt6-0.1.0.dist-info/WHEEL
custompyqt6-0.1.0.dist-info/top_level.txt
custompyqt6-0.1.0.dist-info/RECORD
