Metadata-Version: 2.4
Name: CustomPyQt6
Version: 0.1.0
Summary: Упрощенная библиотека для создания красивых приложений на PyQt6
Home-page: https://github.com/your_username/CustomPyQt6
Author: MineMish
Author-email: your.email@example.com
Classifier: Programming Language :: Python :: 3
Classifier: License :: OSI Approved :: MIT License
Classifier: Operating System :: OS Independent
Requires-Python: >=3.6
Requires-Dist: PyQt6>=6.0.0
Dynamic: author
Dynamic: author-email
Dynamic: classifier
Dynamic: description
Dynamic: description-content-type
Dynamic: home-page
Dynamic: requires-dist
Dynamic: requires-python
Dynamic: summary
